LICENSE
MANIFEST.in
README.rst
setup.cfg
setup.py
versioneer.py
artellapipe/__init__.py
artellapipe/tools/__init__.py
artellapipe/tools/assetslibrary/__init__.py
artellapipe/tools/assetslibrary/__logging__.ini
artellapipe/tools/assetslibrary/__version__.py
artellapipe/tools/assetslibrary/_version.py
artellapipe/tools/assetslibrary/core/__init__.py
artellapipe/tools/assetslibrary/core/assetslibrary.py
artellapipe/tools/assetslibrary/resources/icons/color/assets_library.png
artellapipe/tools/assetslibrary/resources/icons/color/backgroundelements.png
artellapipe/tools/assetslibrary/resources/icons/color/characters.png
artellapipe/tools/assetslibrary/resources/icons/color/home.png
artellapipe/tools/assetslibrary/resources/icons/color/props.png
artellapipe/tools/assetslibrary/resources/images/asset_not_published.png
artellapipe/tools/assetslibrary/resources/images/assetslibrary_logo.png
artellapipe/tools/assetslibrary/resources/images/loading_assets.png
artellapipe/tools/assetslibrary/resources/images/no_assets_found.png
artellapipe/tools/assetslibrary/widgets/__init__.py
artellapipe/tools/assetslibrary/widgets/assetslibrary.py
artellapipe_tools_assetslibrary.egg-info/PKG-INFO
artellapipe_tools_assetslibrary.egg-info/SOURCES.txt
artellapipe_tools_assetslibrary.egg-info/dependency_links.txt
artellapipe_tools_assetslibrary.egg-info/not-zip-safe
artellapipe_tools_assetslibrary.egg-info/requires.txt
artellapipe_tools_assetslibrary.egg-info/top_level.txt
tests/__init__.py
tests/test_general.py