Metadata-Version: 2.1
Name: artellapipe-tools-assetslibrary
Version: 0.0.9
Summary: Tool to easily import and reference assets file into DCC scene
Home-page: https://github.com/ArtellaPipe/artellapipe-tools-assetslibrary
Author: Tomas Poveda
Author-email: tpovedatd@gmail.com
License: MIT
Platform: UNKNOWN
Provides-Extra: dev
Provides-Extra: test
